note/__init__.py
note/__main__.py
note/controller.py
note/objects.py
note/view.py
note/infrastructure/__init__.py
note/infrastructure/config.py
note/infrastructure/db.py
note/infrastructure/error.py
note/infrastructure/logging.py
note/infrastructure/stdouthelper.py
note/infrastructure/locales/argparse-zh-cn.po
note/infrastructure/locales/zh_CN/LC_MESSAGES/argparse.mo
note/module/__init__.py
note/module/app.py
note/module/argparser.py
note/module/filehandler.py
note/module/pathhelper.py
note/module/reviewer.py
note/module/visitor.py
note/module/element/__init__.py
note/module/markdown/__init__.py
note/module/markdown/filehandler.py
note/module/markdown/qa.py
note/module/markdown/title_pat.py
note/module/qahandler/__init__.py
note/module/qahandler/purgeqahandler.py
note/module/qahandler/reviewqahandler.py
note/utils/__init__.py
note/utils/cached_property.py
note/utils/date.py
note/utils/file_watcher.py
note/utils/review_algorithm.py
note/utils/version.py
note/utils/os/__init__.py
note/utils/os/fs.py
note/utils/pattern/__init__.py
note/utils/pattern/singleton.py
urnote-0.4.dist-info/LICENSE
urnote-0.4.dist-info/METADATA
urnote-0.4.dist-info/WHEEL
urnote-0.4.dist-info/entry_points.txt
urnote-0.4.dist-info/top_level.txt
urnote-0.4.dist-info/RECORD
